download_and_extract/__init__.py
download_and_extract/fetcher.py
download_and_extract-0.3.3.dist-info/WHEEL
download_and_extract-0.3.3.dist-info/METADATA
download_and_extract-0.3.3.dist-info/RECORD
