Metadata-Version: 2.1
Name: download-and-extract
Version: 0.3.3
Summary: Downloads zip archive and extracts it to specified folder
Author: Advaita Krishna das
Author-email: advaita.krishna.das@gmail.com
Requires-Python: >=3.7,<4.0
Classifier: Programming Language :: Python :: 3
Classifier: Programming Language :: Python :: 3.7
Requires-Dist: requests (>=2.22,<3.0)
